lesson_1/tasks/04_onehot/bin_to_onehot.sv
module bin_to_onehot(
    input   logic [5:0]bin,
    output  logic [63:0]onehot
);
always_comb begin
    onehot = 64'b0; 
    onehot[bin] = 1'b1; 
end
endmodule

lesson_1/tasks/04_onehot/testbench.sv
`timescale 1ns/1ps

module testbench;

    // 5-битный входной сигнал
    logic [5:0] bin;

    // TODO:
    // Определите разрядность выходного
    // one-hot сигнала
    logic [63:0] onehot;

    // Тестируемый модуль: one-hot кодировщик
    // Соответствие выхода входу:
    // bin =  0 | onehot = 0...001
    // bin =  1 | onehot = 0...010
    // bin =  2 | onehot = 0...100
    // ...
    // bin = 63 | onehot = 1...000
    bin_to_onehot DUT (
        .bin  ( bin  ),
        .onehot ( onehot )
    );

    `include "checker.svh"

    // TODO:
    // Сгенерируйте все возможные входные воздействия и проверки.
    // Как думаете, есть ли способ компактнее, чем copy-paste?
    //
    // В конце симуляции будет выведена статистика о том, какая
    // часть из требуемых значений была подана. Для оценки того,
    // значения из какого интервала не были поданы, воспользуйтесь
    // отчетом 04_onehot/stats/covsummary.html (отчет сформируется
    // после завершения симуляции).

    // Пишите внутри этого блока. Можно использовать подход из
    // нескольких initial, можно из одного. 
    //------------------------------------------------------------
    localparam MAX_BIT = 64 ;
    event ev;
    initial begin
        for (int i = 0; i<MAX_BIT; i++) begin
        #9
        bin = i;
        #1; ->> ev;
        end
    end
    initial begin
        while(1) begin
            @ev;
            if( onehot[bin] === 1'b1 ) begin
                automatic int left = bin + 1;
                automatic int right      = 0;
                automatic int left_ones  = 0;
                automatic int right_ones = 0;
                for (int i = left; i < MAX_BIT; i++) begin
                    if (onehot[i] === 1'b1) begin
                        left_ones = 1;
                        $error("BAD");
                        break;
                    end
                end
                for (int i = right; i < bin; i++) begin
                    if (onehot[i] === 1'b1) begin
                        right_ones = 1;
                        $error("BAD");
                        break;
                    end
                end
                if(left_ones === 0 && right_ones === 0) begin
                    $display("GOOD bin = %d , onehot[%d] = 1 ", bin,bin);
                end
                
            end 
            else $error("BAD");
            if(bin == 63) -> gen_done;
        end
    end
    //------------------------------------------------------------
    
endmodule

lesson_1/tasks/04_onehot/out/sim.vcd
$date
	Tue May  7 21:49:20 2024
$end
$version
	QuestaSim Version 10.7c
$end
$timescale
	1ps
$end

$scope module testbench $end
$var reg 6 ! bin [5:0] $end
$var reg 64 " onehot [63:0] $end
$var event 1 # gen_done $end
$upscope $end
$enddefinitions $end
#0
$dumpvars
b1 !
b10 "
1#
$end
#100000
b10 !
b100 "
#200000
b11 !
b1000 "
#300000
b100 !
b10000 "
#400000
b101 !
b100000 "
#500000
b110 !
b1000000 "
#600000
b111 !
b10000000 "
#700000
b1000 !
b100000000 "
#800000
b1001 !
b1000000000 "
#900000
b1010 !
b10000000000 "
#1000000
b1011 !
b100000000000 "
#1100000
b1100 !
b1000000000000 "
#1200000
b1101 !
b10000000000000 "
#1300000
b1110 !
b100000000000000 "
#1400000
b1111 !
b1000000000000000 "
#1500000
b10000 !
b10000000000000000 "
#1600000
b10001 !
b100000000000000000 "
#1700000
b10010 !
b1000000000000000000 "
#1800000
b10011 !
b10000000000000000000 "
#1900000
b10100 !
b100000000000000000000 "
#2000000
b10101 !
b1000000000000000000000 "
#2100000
b10110 !
b10000000000000000000000 "
#2200000
b10111 !
b100000000000000000000000 "
#2300000
b11000 !
b1000000000000000000000000 "
#2400000
b11001 !
b10000000000000000000000000 "
#2500000
b11010 !
b100000000000000000000000000 "
#2600000
b11011 !
b1000000000000000000000000000 "
#2700000
b11100 !
b10000000000000000000000000000 "
#2800000
b11101 !
b100000000000000000000000000000 "
#2900000
b11110 !
b1000000000000000000000000000000 "
#3000000
b11111 !
b10000000000000000000000000000000 "
#3100000
b100000 !
b100000000000000000000000000000000 "
#3200000
b100001 !
b1000000000000000000000000000000000 "
#3300000
b100010 !
b10000000000000000000000000000000000 "
#3400000
b100011 !
b100000000000000000000000000000000000 "
#3500000
b100100 !
b1000000000000000000000000000000000000 "
#3600000
b100101 !
b10000000000000000000000000000000000000 "
#3700000
b100110 !
b100000000000000000000000000000000000000 "
#3800000
b100111 !
b1000000000000000000000000000000000000000 "
#3900000
b101000 !
b10000000000000000000000000000000000000000 "
#4000000
b101001 !
b100000000000000000000000000000000000000000 "
#4100000
b101010 !
b1000000000000000000000000000000000000000000 "
#4200000
b101011 !
b10000000000000000000000000000000000000000000 "
#4300000
b101100 !
b100000000000000000000000000000000000000000000 "
#4400000
b101101 !
b1000000000000000000000000000000000000000000000 "
#4500000
b101110 !
b10000000000000000000000000000000000000000000000 "
#4600000
b101111 !
b100000000000000000000000000000000000000000000000 "
#4700000
b110000 !
b1000000000000000000000000000000000000000000000000 "
#4800000
b110001 !
b10000000000000000000000000000000000000000000000000 "
#4900000
b110010 !
b100000000000000000000000000000000000000000000000000 "
#5000000
b110011 !
b1000000000000000000000000000000000000000000000000000 "
#5100000
b110100 !
b10000000000000000000000000000000000000000000000000000 "
#5200000
b110101 !
b100000000000000000000000000000000000000000000000000000 "
#5300000
b110110 !
b1000000000000000000000000000000000000000000000000000000 "
#5400000
b110111 !
b10000000000000000000000000000000000000000000000000000000 "
#5500000
b111000 !
b100000000000000000000000000000000000000000000000000000000 "
#5600000
b111001 !
b1000000000000000000000000000000000000000000000000000000000 "
#5700000
b111010 !
b10000000000000000000000000000000000000000000000000000000000 "
#5800000
b111011 !
b100000000000000000000000000000000000000000000000000000000000 "
#5900000
b111100 !
b1000000000000000000000000000000000000000000000000000000000000 "
#6000000
b111101 !
b10000000000000000000000000000000000000000000000000000000000000 "
#6100000
b111110 !
b100000000000000000000000000000000000000000000000000000000000000 "
#6200000
b111111 !
b0 "
