lesson_1/tasks/04_onehot/bin_to_onehot.sv
module bin_to_onehot(
    input   logic [5:0]bin,
    output  logic [63:0]onehot
);
always_comb begin
    onehot = 64'b0; 
    onehot[bin] = 1'b1; 
end
endmodule

lesson_1/tasks/04_onehot/testbench.sv
`timescale 1ns/1ps

module testbench;

    // 5-битный входной сигнал
    logic [5:0] bin;

    // TODO:
    // Определите разрядность выходного
    // one-hot сигнала
    logic [63:0] onehot;

    // Тестируемый модуль: one-hot кодировщик
    // Соответствие выхода входу:
    // bin =  0 | onehot = 0...001
    // bin =  1 | onehot = 0...010
    // bin =  2 | onehot = 0...100
    // ...
    // bin = 63 | onehot = 1...000
    bin_to_onehot DUT (
        .bin  ( bin  ),
        .onehot ( onehot )
    );

    `include "checker.svh"

    // TODO:
    // Сгенерируйте все возможные входные воздействия и проверки.
    // Как думаете, есть ли способ компактнее, чем copy-paste?
    //
    // В конце симуляции будет выведена статистика о том, какая
    // часть из требуемых значений была подана. Для оценки того,
    // значения из какого интервала не были поданы, воспользуйтесь
    // отчетом 04_onehot/stats/covsummary.html (отчет сформируется
    // после завершения симуляции).

    // Пишите внутри этого блока. Можно использовать подход из
    // нескольких initial, можно из одного. 
    //------------------------------------------------------------
    localparam MAX_BIT = 64 ;
    event ev;
    initial begin
        for (int i = 0; i<MAX_BIT; i++) begin
        #9
        bin = i;
        #1; ->> ev;
        end
    end
    initial begin
        while(1) begin
            @ev;
            if( onehot[bin] === 1'b1 ) begin
                automatic int left = bin + 1;
                automatic int right      = 0;
                automatic int left_ones  = 0;
                automatic int right_ones = 0;
                for (int i = left; i < MAX_BIT; i++) begin
                    if (onehot[i] === 1'b1) begin
                        left_ones = 1;
                        $error("BAD");
                        break;
                    end
                end
                for (int i = right; i < bin; i++) begin
                    if (onehot[i] === 1'b1) begin
                        right_ones = 1;
                        $error("BAD");
                        break;
                    end
                end
                if(left_ones === 0 && right_ones === 0) begin
                    $display("GOOD bin = %d , onehot[%d] = 1 ", bin,bin);
                end
                
            end 
            else $error("BAD");
            if(bin == 63) -> gen_done;
        end
    end
    //------------------------------------------------------------
    
endmodule

lesson_1/tasks/04_onehot/out/sim.vcd
$date
	Sun May  5 01:33:33 2024
$end
$version
	QuestaSim Version 10.7c
$end
$timescale
	1ps
$end

$scope module testbench $end
$var reg 6 ! bin [5:0] $end
$var reg 64 " onehot [63:0] $end
$var event 1 # gen_done $end
$var event 1 $ ev $end
$upscope $end
$enddefinitions $end
#0
$dumpvars
bx !
bx "
1#
1$
$end
#9000
b0 !
b1 "
#10000
1$
#19000
b1 !
b10 "
#20000
1$
#29000
b10 !
b100 "
#30000
1$
#39000
b11 !
b1000 "
#40000
1$
#49000
b100 !
b10000 "
#50000
1$
#59000
b101 !
b100000 "
#60000
1$
#69000
b110 !
b1000000 "
#70000
1$
#79000
b111 !
b10000000 "
#80000
1$
#89000
b1000 !
b100000000 "
#90000
1$
#99000
b1001 !
b1000000000 "
#100000
1$
#109000
b1010 !
b10000000000 "
#110000
1$
#119000
b1011 !
b100000000000 "
#120000
1$
#129000
b1100 !
b1000000000000 "
#130000
1$
#139000
b1101 !
b10000000000000 "
#140000
1$
#149000
b1110 !
b100000000000000 "
#150000
1$
#159000
b1111 !
b1000000000000000 "
#160000
1$
#169000
b10000 !
b10000000000000000 "
#170000
1$
#179000
b10001 !
b100000000000000000 "
#180000
1$
#189000
b10010 !
b1000000000000000000 "
#190000
1$
#199000
b10011 !
b10000000000000000000 "
#200000
1$
#209000
b10100 !
b100000000000000000000 "
#210000
1$
#219000
b10101 !
b1000000000000000000000 "
#220000
1$
#229000
b10110 !
b10000000000000000000000 "
#230000
1$
#239000
b10111 !
b100000000000000000000000 "
#240000
1$
#249000
b11000 !
b1000000000000000000000000 "
#250000
1$
#259000
b11001 !
b10000000000000000000000000 "
#260000
1$
#269000
b11010 !
b100000000000000000000000000 "
#270000
1$
#279000
b11011 !
b1000000000000000000000000000 "
#280000
1$
#289000
b11100 !
b10000000000000000000000000000 "
#290000
1$
#299000
b11101 !
b100000000000000000000000000000 "
#300000
1$
#309000
b11110 !
b1000000000000000000000000000000 "
#310000
1$
#319000
b11111 !
b10000000000000000000000000000000 "
#320000
1$
#329000
b100000 !
b100000000000000000000000000000000 "
#330000
1$
#339000
b100001 !
b1000000000000000000000000000000000 "
#340000
1$
#349000
b100010 !
b10000000000000000000000000000000000 "
#350000
1$
#359000
b100011 !
b100000000000000000000000000000000000 "
#360000
1$
#369000
b100100 !
b1000000000000000000000000000000000000 "
#370000
1$
#379000
b100101 !
b10000000000000000000000000000000000000 "
#380000
1$
#389000
b100110 !
b100000000000000000000000000000000000000 "
#390000
1$
#399000
b100111 !
b1000000000000000000000000000000000000000 "
#400000
1$
#409000
b101000 !
b10000000000000000000000000000000000000000 "
#410000
1$
#419000
b101001 !
b100000000000000000000000000000000000000000 "
#420000
1$
#429000
b101010 !
b1000000000000000000000000000000000000000000 "
#430000
1$
#439000
b101011 !
b10000000000000000000000000000000000000000000 "
#440000
1$
#449000
b101100 !
b100000000000000000000000000000000000000000000 "
#450000
1$
#459000
b101101 !
b1000000000000000000000000000000000000000000000 "
#460000
1$
#469000
b101110 !
b10000000000000000000000000000000000000000000000 "
#470000
1$
#479000
b101111 !
b100000000000000000000000000000000000000000000000 "
#480000
1$
#489000
b110000 !
b1000000000000000000000000000000000000000000000000 "
#490000
1$
#499000
b110001 !
b10000000000000000000000000000000000000000000000000 "
#500000
1$
#509000
b110010 !
b100000000000000000000000000000000000000000000000000 "
#510000
1$
#519000
b110011 !
b1000000000000000000000000000000000000000000000000000 "
#520000
1$
#529000
b110100 !
b10000000000000000000000000000000000000000000000000000 "
#530000
1$
#539000
b110101 !
b100000000000000000000000000000000000000000000000000000 "
#540000
1$
#549000
b110110 !
b1000000000000000000000000000000000000000000000000000000 "
#550000
1$
#559000
b110111 !
b10000000000000000000000000000000000000000000000000000000 "
#560000
1$
#569000
b111000 !
b100000000000000000000000000000000000000000000000000000000 "
#570000
1$
#579000
b111001 !
b1000000000000000000000000000000000000000000000000000000000 "
#580000
1$
#589000
b111010 !
b10000000000000000000000000000000000000000000000000000000000 "
#590000
1$
#599000
b111011 !
b100000000000000000000000000000000000000000000000000000000000 "
#600000
1$
#609000
b111100 !
b1000000000000000000000000000000000000000000000000000000000000 "
#610000
1$
#619000
b111101 !
b10000000000000000000000000000000000000000000000000000000000000 "
#620000
1$
#629000
b111110 !
b100000000000000000000000000000000000000000000000000000000000000 "
#630000
1$
#639000
b111111 !
b0 "
#640000
1$
1#
