lesson_1/tasks/04_onehot/bin_to_onehot.sv
module bin_to_onehot(
    input   logic [5:0]bin,
    output  logic [63:0]onehot
);
always_comb begin
    onehot = 64'b0; 
    onehot[bin] = 1'b1; 
end
endmodule

lesson_1/tasks/04_onehot/testbench.sv
`timescale 1ns/1ps

module testbench;

    // 5-битный входной сигнал
    logic [5:0] bin;

    // TODO:
    // Определите разрядность выходного
    // one-hot сигнала
    logic [63:0] onehot;

    // Тестируемый модуль: one-hot кодировщик
    // Соответствие выхода входу:
    // bin =  0 | onehot = 0...001
    // bin =  1 | onehot = 0...010
    // bin =  2 | onehot = 0...100
    // ...
    // bin = 63 | onehot = 1...000
    bin_to_onehot DUT (
        .bin  ( bin  ),
        .onehot ( onehot )
    );

    `include "checker.svh"

    // TODO:
    // Сгенерируйте все возможные входные воздействия и проверки.
    // Как думаете, есть ли способ компактнее, чем copy-paste?
    //
    // В конце симуляции будет выведена статистика о том, какая
    // часть из требуемых значений была подана. Для оценки того,
    // значения из какого интервала не были поданы, воспользуйтесь
    // отчетом 04_onehot/stats/covsummary.html (отчет сформируется
    // после завершения симуляции).

    // Пишите внутри этого блока. Можно использовать подход из
    // нескольких initial, можно из одного. 
    //------------------------------------------------------------
    localparam MAX_BIT = 64 ;
    event ev;
    initial begin
        for (int i = 0; i<MAX_BIT; i++) begin
        #9
        bin = i;
        #1; ->> ev;
        end
    end
    initial begin
        while(1) begin
            @ev;
            if( onehot[bin] === 1'b1 ) begin
                automatic int left = bin + 1;
                automatic int right      = 0;
                automatic int left_ones  = 0;
                automatic int right_ones = 0;
                for (int i = left; i < MAX_BIT; i++) begin
                    if (onehot[i] === 1'b1) begin
                        left_ones = 1;
                        $error("BAD");
                        break;
                    end
                end
                for (int i = right; i < bin; i++) begin
                    if (onehot[i] === 1'b1) begin
                        right_ones = 1;
                        $error("BAD");
                        break;
                    end
                end
                if(left_ones === 0 && right_ones === 0) begin
                    $display("GOOD bin = %d , onehot[%d] = 1 ", bin,bin);
                end
                
            end 
            else $error("BAD");
            if(bin == 63) -> gen_done;
        end
    end
    //------------------------------------------------------------
    
endmodule

lesson_1/tasks/04_onehot/out/sim.vcd
$date
	Mon Jun  3 10:45:16 2024
$end
$version
	QuestaSim Version 10.7c
$end
$timescale
	1ps
$end

$scope module testbench $end
$var reg 6 ! bin [5:0] $end
$var reg 64 " onehot [63:0] $end
$var event 1 # gen_done $end
$upscope $end
$enddefinitions $end
#0
$dumpvars
b0 !
b1 "
1#
$end
#1000
b1 !
b10 "
#2000
b10 !
b100 "
#3000
b11 !
b1000 "
#4000
b100 !
b10000 "
#5000
b101 !
b100000 "
#6000
b110 !
b1000000 "
#7000
b111 !
b10000000 "
#8000
b1000 !
b100000000 "
#9000
b1001 !
b1000000000 "
#10000
b1010 !
b10000000000 "
#11000
b1011 !
b100000000000 "
#12000
b1100 !
b1000000000000 "
#13000
b1101 !
b10000000000000 "
#14000
b1110 !
b100000000000000 "
#15000
b1111 !
b1000000000000000 "
#16000
b10000 !
b10000000000000000 "
#17000
b10001 !
b100000000000000000 "
#18000
b10010 !
b1000000000000000000 "
#19000
b10011 !
b10000000000000000000 "
#20000
b10100 !
b100000000000000000000 "
#21000
b10101 !
b1000000000000000000000 "
#22000
b10110 !
b10000000000000000000000 "
#23000
b10111 !
b100000000000000000000000 "
#24000
b11000 !
b1000000000000000000000000 "
#25000
b11001 !
b10000000000000000000000000 "
#26000
b11010 !
b100000000000000000000000000 "
#27000
b11011 !
b1000000000000000000000000000 "
#28000
b11100 !
b10000000000000000000000000000 "
#29000
b11101 !
b100000000000000000000000000000 "
#30000
b11110 !
b1000000000000000000000000000000 "
#31000
b11111 !
b10000000000000000000000000000000 "
#32000
b100000 !
b100000000000000000000000000000000 "
#33000
b100001 !
b1000000000000000000000000000000000 "
#34000
b100010 !
b10000000000000000000000000000000000 "
#35000
b100011 !
b100000000000000000000000000000000000 "
#36000
b100100 !
b1000000000000000000000000000000000000 "
#37000
b100101 !
b10000000000000000000000000000000000000 "
#38000
b100110 !
b100000000000000000000000000000000000000 "
#39000
b100111 !
b1000000000000000000000000000000000000000 "
#40000
b101000 !
b10000000000000000000000000000000000000000 "
#41000
b101001 !
b100000000000000000000000000000000000000000 "
#42000
b101010 !
b1000000000000000000000000000000000000000000 "
#43000
b101011 !
b10000000000000000000000000000000000000000000 "
#44000
b101100 !
b100000000000000000000000000000000000000000000 "
#45000
b101101 !
b1000000000000000000000000000000000000000000000 "
#46000
b101110 !
b10000000000000000000000000000000000000000000000 "
#47000
b101111 !
b100000000000000000000000000000000000000000000000 "
#48000
b110000 !
b1000000000000000000000000000000000000000000000000 "
#49000
b110001 !
b10000000000000000000000000000000000000000000000000 "
#50000
b110010 !
b100000000000000000000000000000000000000000000000000 "
#51000
b110011 !
b1000000000000000000000000000000000000000000000000000 "
#52000
b110100 !
b10000000000000000000000000000000000000000000000000000 "
#53000
b110101 !
b100000000000000000000000000000000000000000000000000000 "
#54000
b110110 !
b1000000000000000000000000000000000000000000000000000000 "
#55000
b110111 !
b10000000000000000000000000000000000000000000000000000000 "
#56000
b111000 !
b100000000000000000000000000000000000000000000000000000000 "
#57000
b111001 !
b1000000000000000000000000000000000000000000000000000000000 "
#58000
b111010 !
b10000000000000000000000000000000000000000000000000000000000 "
#59000
b111011 !
b100000000000000000000000000000000000000000000000000000000000 "
#60000
b111100 !
b1000000000000000000000000000000000000000000000000000000000000 "
#61000
b111101 !
b10000000000000000000000000000000000000000000000000000000000000 "
#62000
b111110 !
b100000000000000000000000000000000000000000000000000000000000000 "
#63000
b111111 !
b0 "
